codewords_core/__init__.py
codewords_core/file_type_utils.py
codewords_core/io_metadata.py
codewords_core/io_metadata_test.py
codewords_core-0.1.0.dist-info/METADATA
codewords_core-0.1.0.dist-info/WHEEL
codewords_core-0.1.0.dist-info/top_level.txt
codewords_core-0.1.0.dist-info/RECORD
